{
  "swagger": "2.0",
  "info": {
    "title": "Users API",
    "description": "Users API",
    "version": "1.0.0"
  },
  "basePath": "/",
  "schemes": [
    "https",
    "http"
  ],
  "paths": {
    "/events/": {
      "get": {
        "description": "",
        "responses": {
          "200": {
            "description": "OK"
          },
          "500": {
            "description": "Internal Server Error"
          }
        }
      },
      "post": {
        "description": "",
        "responses": {
          "200": {
            "description": "OK"
          }
        }
      }
    },
    "/events/{id}": {
      "get": {
        "description": "",
        "parameters": [
          {
            "name": "id",
            "in": "path",
            "required": true,
            "type": "string"
          }
        ],
        "responses": {
          "200": {
            "description": "OK"
          },
          "404": {
            "description": "Not Found"
          }
        }
      },
      "patch": {
        "description": "",
        "parameters": [
          {
            "name": "id",
            "in": "path",
            "required": true,
            "type": "string"
          }
        ],
        "responses": {
          "200": {
            "description": "OK"
          }
        }
      },
      "delete": {
        "description": "",
        "parameters": [
          {
            "name": "id",
            "in": "path",
            "required": true,
            "type": "string"
          }
        ],
        "responses": {
          "200": {
            "description": "OK"
          }
        }
      }
    },
    "/users/": {
      "get": {
        "tags": [
          "Users"
        ],
        "description": "",
        "responses": {
          "default": {
            "description": ""
          }
        }
      },
      "post": {
        "tags": [
          "Users"
        ],
        "description": "",
        "responses": {
          "default": {
            "description": ""
          }
        }
      }
    },
    "/users/{id}": {
      "get": {
        "tags": [
          "Users"
        ],
        "description": "",
        "parameters": [
          {
            "name": "id",
            "in": "path",
            "required": true,
            "type": "string"
          }
        ],
        "responses": {
          "default": {
            "description": ""
          }
        }
      },
      "patch": {
        "tags": [
          "Users"
        ],
        "description": "",
        "parameters": [
          {
            "name": "id",
            "in": "path",
            "required": true,
            "type": "string"
          }
        ],
        "responses": {
          "default": {
            "description": ""
          }
        }
      },
      "delete": {
        "tags": [
          "Users"
        ],
        "description": "",
        "parameters": [
          {
            "name": "id",
            "in": "path",
            "required": true,
            "type": "string"
          }
        ],
        "responses": {
          "default": {
            "description": ""
          }
        }
      }
    },
    "/timers/": {
      "get": {
        "tags": [
          "Timers"
        ],
        "description": "",
        "responses": {
          "default": {
            "description": ""
          }
        }
      },
      "post": {
        "tags": [
          "Timers"
        ],
        "description": "",
        "responses": {
          "default": {
            "description": ""
          }
        }
      }
    },
    "/timers/{id}": {
      "get": {
        "tags": [
          "Timers"
        ],
        "description": "",
        "parameters": [
          {
            "name": "id",
            "in": "path",
            "required": true,
            "type": "string"
          }
        ],
        "responses": {
          "default": {
            "description": ""
          }
        }
      },
      "patch": {
        "tags": [
          "Timers"
        ],
        "description": "",
        "parameters": [
          {
            "name": "id",
            "in": "path",
            "required": true,
            "type": "string"
          }
        ],
        "responses": {
          "default": {
            "description": ""
          }
        }
      },
      "delete": {
        "tags": [
          "Timers"
        ],
        "description": "",
        "parameters": [
          {
            "name": "id",
            "in": "path",
            "required": true,
            "type": "string"
          }
        ],
        "responses": {
          "default": {
            "description": ""
          }
        }
      }
    },
    "/routines/": {
      "get": {
        "tags": [
          "Routines"
        ],
        "description": "",
        "responses": {
          "default": {
            "description": ""
          }
        }
      },
      "post": {
        "tags": [
          "Routines"
        ],
        "description": "",
        "responses": {
          "default": {
            "description": ""
          }
        }
      }
    },
    "/routines/{id}": {
      "get": {
        "tags": [
          "Routines"
        ],
        "description": "",
        "parameters": [
          {
            "name": "id",
            "in": "path",
            "required": true,
            "type": "string"
          }
        ],
        "responses": {
          "default": {
            "description": ""
          }
        }
      },
      "patch": {
        "tags": [
          "Routines"
        ],
        "description": "",
        "parameters": [
          {
            "name": "id",
            "in": "path",
            "required": true,
            "type": "string"
          }
        ],
        "responses": {
          "default": {
            "description": ""
          }
        }
      },
      "delete": {
        "tags": [
          "Routines"
        ],
        "description": "",
        "parameters": [
          {
            "name": "id",
            "in": "path",
            "required": true,
            "type": "string"
          }
        ],
        "responses": {
          "default": {
            "description": ""
          }
        }
      }
    },
    "/api-docs": {
      "get": {
        "description": "",
        "responses": {
          "default": {
            "description": ""
          }
        }
      }
    },
    "/": {
      "get": {
        "tags": [
          "Home"
        ],
        "description": "",
        "responses": {
          "200": {
            "description": "OK"
          }
        }
      }
    },
    "/auth": {
      "get": {
        "description": "",
        "responses": {
          "default": {
            "description": ""
          }
        }
      }
    },
    "/users": {
      "get": {
        "tags": [
          "Users"
        ],
        "description": "",
        "responses": {
          "default": {
            "description": ""
          }
        }
      }
    },
    "/events": {
      "get": {
        "tags": [
          "Events"
        ],
        "description": "",
        "responses": {
          "default": {
            "description": ""
          }
        }
      }
    },
    "/timers": {
      "get": {
        "tags": [
          "Timers"
        ],
        "description": "",
        "responses": {
          "default": {
            "description": ""
          }
        }
      }
    },
    "/routines": {
      "get": {
        "tags": [
          "Routines"
        ],
        "description": "",
        "responses": {
          "default": {
            "description": ""
          }
        }
      }
    }
  }
}